axiompy/__init__.py
axiompy/unit.py
axiompy/units.py
axiompy/value.py
axiompy/db/en_units.acf
axiompy-0.2.1.dist-info/LICENSE
axiompy-0.2.1.dist-info/METADATA
axiompy-0.2.1.dist-info/WHEEL
axiompy-0.2.1.dist-info/top_level.txt
axiompy-0.2.1.dist-info/RECORD
