Metadata-Version: 2.1
Name: axiompy
Version: 0.2.1
Summary: Unit Conversions and other math
Home-page: https://github.com/ArztKlein/Axiompy
Author: ArztKlein
Author-email: 
Keywords: python,unit conversion,units
Requires-Python: >3.6.1
License-File: LICENSE
Requires-Dist: acfile
